tcpw/__init__.py
tcpw/__main__.py
tcpw/tcpw
tcpw_armv7l-0.1.9.dist-info/METADATA
tcpw_armv7l-0.1.9.dist-info/WHEEL
tcpw_armv7l-0.1.9.dist-info/entry_points.txt
tcpw_armv7l-0.1.9.dist-info/top_level.txt
tcpw_armv7l-0.1.9.dist-info/RECORD
